dataweave_py-0.2.0.dist-info/licenses/LICENSE
dwpy/__init__.py
dwpy/builtins.py
dwpy/parser.py
dwpy/pydantic_export.py
dwpy/runtime.py
dwpy/type_inference.py
dwpy/typesystem.py
dwpy/modules/dw/Core.dwl
dwpy/modules/dw/Crypto.dwl
dwpy/modules/dw/Runtime.dwl
dwpy/modules/dw/System.dwl
dwpy/modules/dw/core/Arrays.dwl
dwpy/modules/dw/core/Binaries.dwl
dwpy/modules/dw/core/Dates.dwl
dwpy/modules/dw/core/Numbers.dwl
dwpy/modules/dw/core/Objects.dwl
dwpy/modules/dw/extension/DataFormat.dwl
dwpy/modules/dw/module/Mime.dwl
dwpy/modules/dw/module/Multipart.dwl
dwpy/modules/dw/util/Coercions.dwl
dwpy/modules/dw/util/Diff.dwl
dwpy/modules/dw/util/Math.dwl
dwpy/modules/dw/util/Timer.dwl
dwpy/modules/dw/util/Tree.dwl
dwpy/modules/dw/util/Values.dwl
dwpy/modules/dw/xml/Dtd.dwl
dataweave_py-0.2.0.dist-info/METADATA
dataweave_py-0.2.0.dist-info/WHEEL
dataweave_py-0.2.0.dist-info/top_level.txt
dataweave_py-0.2.0.dist-info/RECORD
