Metadata-Version: 2.4
Name: dataweave-py
Version: 0.2.0
Summary: DataWeave interpreter running natively on Python
Author-email: Esteban Wasinger <estebanwasinger@gmail.com>
Maintainer-email: Esteban Wasinger <estebanwasinger@gmail.com>
License: MIT
Project-URL: Homepage, https://github.com/estebanwasinger/dataweave-py
Project-URL: Documentation, https://github.com/estebanwasinger/dataweave-py#readme
Project-URL: Repository, https://github.com/estebanwasinger/dataweave-py
Project-URL: Issues, https://github.com/estebanwasinger/dataweave-py/issues
Keywords: dataweave,data-transformation,etl,mulesoft,interpreter,functional-programming
Classifier: Development Status :: 3 - Alpha
Classifier: Intended Audience :: Developers
Classifier: Topic :: Software Development :: Interpreters
Classifier: Topic :: Software Development :: Libraries :: Python Modules
Classifier: License :: OSI Approved :: MIT License
Classifier: Programming Language :: Python :: 3
Classifier: Programming Language :: Python :: 3.10
Classifier: Programming Language :: Python :: 3.11
Classifier: Programming Language :: Python :: 3.12
Classifier: Programming Language :: Python :: 3.13
Classifier: Operating System :: OS Independent
Requires-Python: >=3.10
License-File: LICENSE
Requires-Dist: pandas>=2.3.3
Requires-Dist: pydantic>=2.12.3
Provides-Extra: dev
Requires-Dist: pytest>=8.4.2; extra == "dev"
Requires-Dist: ipykernel>=7.1.0; extra == "dev"
Dynamic: license-file
